rupayamn/__init__.py
rupayamn/configuration.py
rupayamn/display.py
rupayamn/elements/__init__.py
rupayamn/elements/network.py
rupayamn/elements/service.py
rupayamn/elements/volume.py
rupayamn/environments.py
rupayamn/rupayamn.py
rupayamn-1.0.7.dist-info/entry_points.txt
rupayamn-1.0.7.dist-info/WHEEL
rupayamn-1.0.7.dist-info/METADATA
rupayamn-1.0.7.dist-info/RECORD
